[
{       
        "name": "Gold Experience",
        "unitType": "Sword",
        "movement": 5,
        "strength": 100,
        "uniqueTo": "Wakanda",
        "uniques": [
            "All adjacent units heal [+30] HP when healing",
            "[+50] HP when healing","Unbuildable"],
        "promotions": ["March", "Medic"]
        "civilopediaText": [
            {"text": "This is resolve! It is to carve out your destined path through the darkened wastes! — Giorno Giovanna"}
        ]
},
    {
        "name": "Pain",
        "unitType": "Sword",
        "movement": 7,
        "strength": 140,
        "uniqueTo": "Wakanda",
        "uniques": [
            "Unbuildable"
        ],
        "promotions": ["Shock I","Drill I", "Blitz"],
        
    },
        {
        "name": "Juubidara",
        "unitType": "Sword",
        "movement": 10,
        "strength": 200,
        "uniqueTo": "Wakanda",
        "uniques": [
            "[This Unit] heals [50] HP <upon entering combat>","Invisible to others","[5] additional attacks per turn"
        ],
        "promotions": ["Shock I","Drill I", "Blitz","March"],
        
    }
            ]
